{
 "song": "Lida Rose",
 "part": "Baritone",
 "scoreVersion": "lida-rose-baritone-six-flat-114",
 "sourcePages": [
  "196:P4",
  "197:P3",
  "198:P3"
 ],
 "generatedAt": "2026-06-26T23:58:58.930Z",
 "keyFifths": -6,
 "noteCount": 114,
 "wholeNotes": [
  {
   "measure": 5,
   "pitch": "Ab3"
  },
  {
   "measure": 9,
   "pitch": "Ab3"
  },
  {
   "measure": 13,
   "pitch": "Cb4"
  },
  {
   "measure": 21,
   "pitch": "Ab3"
  },
  {
   "measure": 29,
   "pitch": "Bb3"
  }
 ],
 "sync": {
  "noteCount": 114,
  "reconciledCount": 114,
  "source": "pure-notation timing from verified MusicXML (no audio)",
  "tempoBpm": 99,
  "secondsPerBeat": 0.606,
  "notationTiming": {
   "ok": true,
   "offBy": 0,
   "detail": "bpm=99; spb=0.606; monotonic=true; offGrid=0/114"
  }
 },
 "checks": [
  {
   "id": "key-fifths",
   "label": "Printed key",
   "status": "pass",
   "detail": "expected -6; xml=-6 normalizer=-6"
  },
  {
   "id": "source-pitches",
   "label": "Source pitch sequence",
   "status": "pass",
   "detail": "114 pitches match pp.196-198"
  },
  {
   "id": "whole-notes",
   "label": "Whole-note survival",
   "status": "pass",
   "detail": "expected [5:Ab3 9:Ab3 13:Cb4 21:Ab3 29:Bb3]; got [5:Ab3 9:Ab3 13:Cb4 21:Ab3 29:Bb3]"
  },
  {
   "id": "note-count",
   "label": "Pitched note count",
   "status": "pass",
   "detail": "expected 114; got 114"
  },
  {
   "id": "printed-score-audit",
   "label": "Printed/source audit",
   "status": "fail",
   "detail": "m9: expected [Cb4:2:half Gb3:2:half], got [Ab3:4:whole] (page-197 Oliver chapel-bell system opening) | m18: expected [Cb4:1:quarter Cb4:1:quarter A3:1:quarter Bb3:1:quarter], got [Db4:0.5:eighth Db4:0.5:eighth Db4:1:quarter Db4:1:quarter] (page-197 Oliver end of sweetheart system) | m31: expected [Gb3:2:half G3:2:half], got [Cb4:1:quarter C4:1:quarter Cb4:2:half] (page-198 Oliver final active Lida Rose measure before page-turn residue)"
  },
  {
   "id": "no-courtesy-clefs",
   "label": "No stray courtesy clefs",
   "status": "pass",
   "detail": "no later clefs in the line"
  },
  {
   "id": "sync-count",
   "label": "Sync target count",
   "status": "pass",
   "detail": "sync=114; reconciled=114; score=114"
  },
  {
   "id": "notation-timing",
   "label": "Pure-notation timing",
   "status": "pass",
   "detail": "source=pure-notation timing from verified MusicXML (no audio); bpm=99; spb=0.606; monotonic=true; offGrid=0/114"
  }
 ]
}
